{
    "total": 13,
    "rows": [
        {
            "id": "1",
            "name": "a1",
            "age": 11
        },
        {
            "id": "2",
            "name": "a2",
            "age": 12
        },
        {
            "id": "3",
            "name": "a3",
            "age": 13
        },
        {
            "id": "4",
            "name": "a4",
            "age": 14
        },
        {
            "id": "5",
            "name": "a5",
            "age": 15
        },
        {
            "id": "6",
            "name": "a6",
            "age": 16
        },
        {
            "id": "7",
            "name": "a7",
            "age": 17
        },
        {
            "id": "8",
            "name": "a8",
            "age": 18
        },
        {
            "id": "9",
            "name": "a9",
            "age": 19
        },
        {
            "id": "10",
            "name": "a10",
            "age": 20
        },
        {
            "id": "11",
            "name": "a11",
            "age": 21
        },
        {
            "id": "12",
            "name": "a12",
            "age": 22
        },
        {
            "id": "13",
            "name": "a13",
            "age": 23
        }
    ]
}